gestion/__main__.py
gestion/addons/__init__.py
gestion/addons/misc.py
gestion/addons/moho.py
gestion/addons/renderers.py
gestion/modules/__init__.py
gestion/modules/cli.py
gestion/modules/config.py
gestion/modules/database.py
gestion/modules/misc.py
gestion/modules/node.py
gestion/modules/queue.py
gestion/modules/tasks.py
gestion/modules/watchfolder.py
gestion/modules/web.py
gestion/web/static/gestion.css~
gestion/web/static/css/gestion.css~
gestion/web/static/css/stylesheet.css
gestion/web/static/css/stylesheet.css~
gestion/web/templates/base.html
gestion/web/templates/base.html~
gestion/web/templates/default.html
gestion/web/templates/default.html~
gestion/web/templates/fullscreen.html
gestion/web/templates/fullscreen.html~
gestion-0.47.dist-info/LICENSE
gestion-0.47.dist-info/METADATA
gestion-0.47.dist-info/WHEEL
gestion-0.47.dist-info/top_level.txt
gestion-0.47.dist-info/RECORD
